rotsim2d_apps/MplCanvas.py
rotsim2d_apps/__init__.py
rotsim2d_apps/peak_picker.py
rotsim2d_apps/rotsim2d_calc.py
rotsim2d_apps/polarizations/AngleWidget.py
rotsim2d_apps/polarizations/PolarizationWidget.py
rotsim2d_apps/polarizations/PolarizationsUI.py
rotsim2d_apps/polarizations/__init__.py
rotsim2d_apps/polarizations/main.py
rotsim2d_apps/waiting_time/ListView.py
rotsim2d_apps/waiting_time/MplWidget.py
rotsim2d_apps/waiting_time/PathwaysWidget.py
rotsim2d_apps/waiting_time/PlotsWidget.py
rotsim2d_apps/waiting_time/Ui_PathwaysWidget.py
rotsim2d_apps/waiting_time/Ui_PlotsWidget.py
rotsim2d_apps/waiting_time/Ui_WaitingTimeWindow.py
rotsim2d_apps/waiting_time/__init__.py
rotsim2d_apps/waiting_time/main.py
rotsim2d_apps-0.3.2.dist-info/LICENSE
rotsim2d_apps-0.3.2.dist-info/METADATA
rotsim2d_apps-0.3.2.dist-info/WHEEL
rotsim2d_apps-0.3.2.dist-info/entry_points.txt
rotsim2d_apps-0.3.2.dist-info/top_level.txt
rotsim2d_apps-0.3.2.dist-info/RECORD
