Metadata-Version: 2.1
Name: rotsim2d-apps
Version: 0.3.2
Summary: Inspect third-order pathways, polarization and waiting-time dependence of 2DIR gas-phase spectra
Home-page: https://github.com/gkowzan/rotsim2d_apps
Author: Grzegorz Kowzan
Author-email: gkowzan@umk.pl
License: MIT License
Classifier: Development Status :: 4 - Beta
Classifier: Environment :: Console
Classifier: Environment :: X11 Applications :: Qt
Classifier: Intended Audience :: Science/Research
Classifier: Programming Language :: Python :: 3
Classifier: Programming Language :: Python :: 3.6
Classifier: Programming Language :: Python :: 3.7
Classifier: Programming Language :: Python :: 3.8
Classifier: Programming Language :: Python :: 3.9
Classifier: Programming Language :: Python :: 3.10
Classifier: Topic :: Scientific/Engineering :: Physics
Classifier: Topic :: Scientific/Engineering :: Chemistry
Classifier: License :: OSI Approved :: MIT License
Requires-Python: >=3.7
License-File: LICENSE
Requires-Dist: rotsim2d (>=0.9.0)
Requires-Dist: numpy (>=1.16.5)
Requires-Dist: asteval (>=0.9.25)
Requires-Dist: toml (>=0.10.2)
Requires-Dist: matplotlib (>=3.3.4)
Requires-Dist: PyQt5
